LICENSE.txt
MANIFEST.in
README.rst
setup.py
pyutopia_plugins_common.egg-info/PKG-INFO
pyutopia_plugins_common.egg-info/SOURCES.txt
pyutopia_plugins_common.egg-info/dependency_links.txt
pyutopia_plugins_common.egg-info/not-zip-safe
pyutopia_plugins_common.egg-info/requires.txt
pyutopia_plugins_common.egg-info/top_level.txt
utopia/plugins/__init__.py
utopia/plugins/common/acs.py
utopia/plugins/common/arxiv.py
utopia/plugins/common/cited.py
utopia/plugins/common/crossref.py
utopia/plugins/common/html.py
utopia/plugins/common/ieee.py
utopia/plugins/common/kend.py
utopia/plugins/common/nature.py
utopia/plugins/common/pmc.py
utopia/plugins/common/pubmed.py
utopia/plugins/common/sciencedirect.py
utopia/plugins/common/wiley.py