Metadata-Version: 1.1
Name: pyutopia-plugins-common
Version: 3.1.0.10
Summary: Utopia common plugins package
Home-page: https://github.com/lostislandlabs/python-utopia-plugins-common
Author: David Thorne
Author-email: davethorne@gmail.com
License:                     GNU GENERAL PUBLIC LICENSE
